{
  "groups": [
    {
      "title": "Tab 页",
      "pages": [
        {
          "html": "index.html",
          "doc": "营销首页.md",
          "label": "营销首页",
          "docUrl": "../docs/miniprogram/pages/营销首页.md",
          "scope": "intro"
        },
        {
          "html": "heroes.html",
          "doc": "英雄广场.md",
          "label": "英雄广场",
          "docUrl": "../docs/miniprogram/pages/英雄广场.md",
          "scope": ""
        },
        {
          "html": "profile.html",
          "doc": "个人中心.md",
          "label": "个人中心",
          "docUrl": "../docs/miniprogram/pages/个人中心.md",
          "scope": ""
        }
      ]
    },
    {
      "title": "浏览与报名",
      "pages": [
        {
          "html": "hero-detail.html",
          "doc": "英雄详情.md",
          "label": "英雄详情",
          "docUrl": "../docs/miniprogram/pages/英雄详情.md",
          "scope": ""
        },
        {
          "html": "recruitment-detail.html",
          "doc": "赛事详情.md",
          "label": "赛事详情",
          "docUrl": "../docs/miniprogram/pages/赛事详情.md",
          "scope": ""
        },
        {
          "html": "activity-detail.html",
          "doc": "活动详情.md",
          "label": "活动详情",
          "docUrl": "../docs/miniprogram/pages/活动详情.md",
          "scope": "intro"
        },
        {
          "html": "course-detail.html",
          "doc": "课程详情.md",
          "label": "课程详情",
          "docUrl": "../docs/miniprogram/pages/课程详情.md",
          "scope": "intro"
        }
      ]
    },
    {
      "title": "英雄认证",
      "pages": [
        {
          "html": "hero-apply.html",
          "doc": "申请成为英雄.md",
          "label": "申请成为英雄",
          "docUrl": "../docs/miniprogram/pages/申请成为英雄.md",
          "scope": ""
        },
        {
          "html": "hero-apply-submitted.html",
          "doc": "申请提交成功.md",
          "label": "申请提交成功",
          "docUrl": "../docs/miniprogram/pages/申请提交成功.md",
          "scope": ""
        }
      ]
    },
    {
      "title": "英雄中心",
      "pages": [
        {
          "html": "recruitment-create.html",
          "doc": "发布招募.md",
          "label": "发布招募",
          "docUrl": "../docs/miniprogram/pages/发布招募.md",
          "scope": ""
        },
        {
          "html": "my-recruitments.html",
          "doc": "我的招募.md",
          "label": "我的招募",
          "docUrl": "../docs/miniprogram/pages/我的招募.md",
          "scope": ""
        },
        {
          "html": "my-courses.html",
          "doc": "我的课程.md",
          "label": "我的课程",
          "docUrl": "../docs/miniprogram/pages/我的课程.md",
          "scope": ""
        },
        {
          "html": "signup-list.html",
          "doc": "报名人员列表.md",
          "label": "报名人员列表",
          "docUrl": "../docs/miniprogram/pages/报名人员列表.md",
          "scope": ""
        }
      ]
    },
    {
      "title": "用户活动",
      "pages": [
        {
          "html": "my-signups.html",
          "doc": "我的报名.md",
          "label": "我的报名",
          "docUrl": "../docs/miniprogram/pages/我的报名.md",
          "scope": ""
        },
        {
          "html": "messages.html",
          "doc": "消息.md",
          "label": "消息",
          "docUrl": "../docs/miniprogram/pages/消息.md",
          "scope": "intro"
        },
        {
          "html": "message-detail.html",
          "doc": "消息详情.md",
          "label": "消息详情",
          "docUrl": "../docs/miniprogram/pages/消息详情.md",
          "scope": ""
        }
      ]
    }
  ]
}
